kivy_garden/qrcode/__init__.py
kivy_garden/qrcode/qrcode_widget.kv
kivy_garden/qrcode/qrcode_widget.py
kivy_garden/qrcode/version.py
kivy_garden.qrcode-2021.314.dist-info/LICENSE
kivy_garden.qrcode-2021.314.dist-info/METADATA
kivy_garden.qrcode-2021.314.dist-info/WHEEL
kivy_garden.qrcode-2021.314.dist-info/top_level.txt
kivy_garden.qrcode-2021.314.dist-info/RECORD
