Metadata-Version: 2.1
Name: kivy_garden.qrcode
Version: 2021.314
Summary: Qrcode generator
Home-page: https://github.com/kivy-garden/qrcode
Author: Kivy
Author-email: kivy@kivy.org
License: UNKNOWN
Platform: UNKNOWN
Requires-Python: >=3
